setup.py
pretty_print_dictionary/__init__.py
pretty_print_dictionary/pretty_dictionary.py
pretty_print_dictionary.egg-info/PKG-INFO
pretty_print_dictionary.egg-info/SOURCES.txt
pretty_print_dictionary.egg-info/dependency_links.txt
pretty_print_dictionary.egg-info/top_level.txt