Metadata-Version: 1.1
Name: pretty-print-dictionary
Version: 1.1.1
Summary: A tool for showing dictionary objects in a more human-readable format.
Home-page: https://github.com/kinghadi/Python-PrettyPrintDictionary
Author: Hadi Sinaee, Sharif University of Technology
Author-email: sinaee@ce.sharif.ir
License: GNU GPL
Keywords: dict dictionary pretty print
Platform: UNKNOWN
Classifier: License :: OSI Approved :: GNU General Public License (GPL)
Classifier: Programming Language :: Python :: 2.7
Classifier: Topic :: Utilities
Classifier: Intended Audience :: Developers
Classifier: Development Status :: 4 - Beta
